Metadata-Version: 1.0
Name: XStatic-D32
Version: 3.5.16.1
Summary: D3 3.5.16 (XStatic packaging standard)
Home-page: http://d3js.org/
Author: Michael Kuty
Author-email: mail@majklk.cz
License: (same as D3)
Keywords: d3 xstatic
Platform: any
